[{"date":"7/4/2014","time":"0:11:00","speed":95,"posted_speed":70,"age":20,"sex":"Female"},{"date":"7/4/2014","time":"0:36:00","speed":95,"posted_speed":70,"age":25,"sex":"Male"},{"date":"7/4/2014","time":"1:02:00","speed":76,"posted_speed":55,"age":25,"sex":"Male"},{"date":"7/4/2014","time":"1:02:00","speed":77,"posted_speed":60,"age":27,"sex":"Male"},{"date":"7/4/2014","time":"1:15:00","speed":83,"posted_speed":70,"age":51,"sex":"Female"},{"date":"7/4/2014","time":"1:33:00","speed":97,"posted_speed":70,"age":29,"sex":"Male"},{"date":"7/4/2014","time":"1:52:00","speed":74,"posted_speed":30,"age":35,"sex":"Male"},{"date":"7/4/2014","time":"3:42:00","speed":66,"posted_speed":55,"age":19,"sex":"Male"},{"date":"7/4/2014","time":"3:51:00","speed":50,"posted_speed":40,"age":25,"sex":"Male"},{"date":"7/4/2014","time":"6:23:00","speed":87,"posted_speed":65,"age":45,"sex":"Male"},{"date":"7/4/2014","time":"6:39:00","speed":93,"posted_speed":70,"age":35,"sex":"Male"},{"date":"7/4/2014","time":"6:43:00","speed":72,"posted_speed":60,"age":46,"sex":"Male"},{"date":"7/4/2014","time":"6:45:00","speed":68,"posted_speed":55,"age":49,"sex":"Female"},{"date":"7/4/2014","time":"6:49:00","speed":88,"posted_speed":70,"age":31,"sex":"Female"},{"date":"7/4/2014","time":"7:00:00","speed":72,"posted_speed":55,"age":60,"sex":"Male"},{"date":"7/4/2014","time":"7:06:00","speed":72,"posted_speed":60,"age":24,"sex":"Male"},{"date":"7/4/2014","time":"7:12:00","speed":72,"posted_speed":60,"age":35,"sex":"Male"},{"date":"7/4/2014","time":"7:15:00","speed":86,"posted_speed":60,"age":17,"sex":"Male"},{"date":"7/4/2014","time":"7:19:00","speed":74,"posted_speed":55,"age":20,"sex":"Male"},{"date":"7/4/2014","time":"7:29:00","speed":70,"posted_speed":55,"age":32,"sex":"Male"},{"date":"7/4/2014","time":"7:33:00","speed":82,"posted_speed":60,"age":46,"sex":"Female"},{"date":"7/4/2014","time":"7:35:00","speed":67,"posted_speed":55,"age":29,"sex":"Male"},{"date":"7/4/2014","time":"7:49:00","speed":62,"posted_speed":50,"age":39,"sex":"Male"}]